us2anonymize/__init__.py
us2anonymize/__main__.py
us2anonymize/anonymize.py
us2anonymize-0.1.1.dist-info/entry_points.txt
us2anonymize-0.1.1.dist-info/WHEEL
us2anonymize-0.1.1.dist-info/METADATA
us2anonymize-0.1.1.dist-info/RECORD
