Metadata-Version: 2.1
Name: us2anonymize
Version: 0.1.1
Summary: 
Author: mathias
Author-email: mathias@us2.ai
Requires-Python: >=3.7.5,<3.11
Classifier: Programming Language :: Python :: 3
Classifier: Programming Language :: Python :: 3.10
Classifier: Programming Language :: Python :: 3.8
Classifier: Programming Language :: Python :: 3.9
Requires-Dist: numpy (>=1.21.3,<2.0.0)
Requires-Dist: opencv-python (<4.5.4)
Requires-Dist: pydicom (>=2.2.2,<3.0.0)
Requires-Dist: python-gdcm (>=3.0.10,<4.0.0)
Requires-Dist: watchdog (>=2.1.6,<3.0.0)
